{
    "contacts": [
                    {
                        "id": 1,
                        "firstName": "paul",
                        "lastName": "kow"
                    },
                    {
                        "id": 2,
                        "firstName": "luke",
                        "lastName": "kow"
                    },
                    {
                        "id": 4,
                        "firstName": "kris",
                        "lastName": "now"
                    },
                    {
                        "id": 4,
                        "firstName": "anna",
                        "lastName": "tom"
                    },
                    {
                        "id": 4,
                        "firstName": "luka",
                        "lastName": "kow"
                    }
    ]
}
